jarmetainforeader/__init__.py
jarmetainforeader/meta_file_reader.py
jarmetainforeader-0.3.1.dist-info/LICENSE
jarmetainforeader-0.3.1.dist-info/METADATA
jarmetainforeader-0.3.1.dist-info/WHEEL
jarmetainforeader-0.3.1.dist-info/top_level.txt
jarmetainforeader-0.3.1.dist-info/RECORD
