Metadata-Version: 2.1
Name: jarmetainforeader
Version: 0.3.1
Summary: Returns the contents of the manifest and pom.properties file of a given jar file in the dictionary format. This is originaly repository https://github.com/badari412/jarmanifestreader. This is forked. I added function to find metainfo file to read pom.properties and MANIFES file
Home-page: https://github.com/secuof/jarmetainforeader.git
Author: David Hong
Author-email: secuof@gmail.com
License: MIT
Download-URL: https://github.com/secuof/jarmetainforeader/archive/master.zip
Keywords: PYTHON,JAR,MANIFEST,POM,JAR INFO READERMANIFESTREADER,READER
Platform: UNKNOWN
Classifier: Development Status :: 5 - Production/Stable
Classifier: Intended Audience :: Developers
Classifier: Topic :: Software Development :: Build Tools
Classifier: License :: OSI Approved :: MIT License
Classifier: Programming Language :: Python :: 3
Classifier: Programming Language :: Python :: 3.4
Classifier: Programming Language :: Python :: 3.5
Classifier: Programming Language :: Python :: 3.6
Classifier: Programming Language :: Python :: 3.7
Requires-Python: >=3
Requires-Dist: xmltodict
